spear_tts_pytorch/__init__.py
spear_tts_pytorch/attend.py
spear_tts_pytorch/data.py
spear_tts_pytorch/distributed.py
spear_tts_pytorch/spear_tts_pytorch.py
spear_tts_pytorch/trainer.py
spear_tts_pytorch-0.4.8.dist-info/LICENSE
spear_tts_pytorch-0.4.8.dist-info/METADATA
spear_tts_pytorch-0.4.8.dist-info/WHEEL
spear_tts_pytorch-0.4.8.dist-info/top_level.txt
spear_tts_pytorch-0.4.8.dist-info/RECORD
