Metadata-Version: 2.1
Name: spear-tts-pytorch
Version: 0.4.8
Summary: Spear-TTS - Pytorch
Home-page: https://github.com/lucidrains/spear-tts-pytorch
Author: Phil Wang
Author-email: lucidrains@gmail.com
License: MIT
Keywords: artificial intelligence,deep learning,transformers,attention mechanism,text-to-speech
Classifier: Development Status :: 4 - Beta
Classifier: Intended Audience :: Developers
Classifier: Topic :: Scientific/Engineering :: Artificial Intelligence
Classifier: License :: OSI Approved :: MIT License
Classifier: Programming Language :: Python :: 3.6
License-File: LICENSE
Requires-Dist: audiolm-pytorch >=1.2.8
Requires-Dist: beartype
Requires-Dist: einops >=0.6.1
Requires-Dist: rotary-embedding-torch >=0.3.0
Requires-Dist: torch >=1.6
Requires-Dist: tqdm
Requires-Dist: x-clip >=0.12.2
